finpull/__init__.py
finpull/__main__.py
finpull/interfaces/__init__.py
finpull/interfaces/cli.py
finpull/interfaces/gui.py
finpull-1.1.0.dist-info/METADATA
finpull-1.1.0.dist-info/WHEEL
finpull-1.1.0.dist-info/entry_points.txt
finpull-1.1.0.dist-info/top_level.txt
finpull-1.1.0.dist-info/RECORD
