Metadata-Version: 2.4
Name: finpull
Version: 1.1.0
Summary: Complete financial data scraper with CLI, GUI, and API interfaces
Home-page: https://github.com/Lavarite/FinPull
Author: Yevhenii Vasylevskyi
Author-email: yevhenii+finpull@vasylevskyi.net
License: MIT
Project-URL: Bug Reports, https://github.com/Lavarite/FinPull/issues
Project-URL: Source, https://github.com/Lavarite/FinPull
Project-URL: Documentation, https://github.com/Lavarite/FinPull/blob/main/README.md
Project-URL: Core Package, https://pypi.org/project/finpull-core/
Keywords: finance,scraping,stocks,financial-data,cli,gui,api,complete,finviz,yahoo-finance
Classifier: Development Status :: 5 - Production/Stable
Classifier: Intended Audience :: Financial and Insurance Industry
Classifier: Intended Audience :: Developers
Classifier: Intended Audience :: End Users/Desktop
Classifier: Topic :: Office/Business :: Financial
Classifier: Topic :: Internet :: WWW/HTTP :: Dynamic Content
Classifier: Topic :: Software Development :: Libraries :: Python Modules
Classifier: Programming Language :: Python :: 3
Classifier: Programming Language :: Python :: 3.7
Classifier: Programming Language :: Python :: 3.8
Classifier: Programming Language :: Python :: 3.9
Classifier: Programming Language :: Python :: 3.10
Classifier: Programming Language :: Python :: 3.11
Classifier: Programming Language :: Python :: 3.12
Classifier: Operating System :: OS Independent
Classifier: Environment :: X11 Applications
Classifier: Environment :: Win32 (MS Windows)
Classifier: Environment :: MacOS X
Classifier: Environment :: Console
Requires-Python: >=3.7
Requires-Dist: finpull-core>=1.1.0
Requires-Dist: openpyxl>=3.0.7
Dynamic: author
Dynamic: author-email
Dynamic: classifier
Dynamic: description
Dynamic: description-content-type
Dynamic: home-page
Dynamic: keywords
Dynamic: license
Dynamic: project-url
Dynamic: requires-dist
Dynamic: requires-python
Dynamic: summary
